locutius/__init__.py
locutius/multimethods.py
locutius-1.0.1.dist-info/METADATA
locutius-1.0.1.dist-info/RECORD
locutius-1.0.1.dist-info/WHEEL
locutius-1.0.1.dist-info/top_level.txt
