Metadata-Version: 2.1
Name: locutius
Version: 1.0.1
Summary: Clojure-style multimethods with arbitrary dispatch keys.
Home-page: https://github.com/rebcabin/locutius
Author: Brian Beckman
Author-email: bc.beckman@gmail.com
License: MIT
Keywords: locutius,multimethod,multimethods,decorator,decorators,dispatch
Platform: UNKNOWN
Classifier: Development Status :: 5 - Production/Stable
Classifier: Programming Language :: Python :: 3
Classifier: Intended Audience :: Developers
Classifier: Topic :: Software Development
Classifier: Operating System :: OS Independent
Classifier: License :: OSI Approved :: MIT License
